cellnition/__init__.py
cellnition/__main__.py
cellnition/error.py
cellnition/main_streamlit.py
cellnition/py.typed
cellnition/types.py
cellnition/_util/__init__.py
cellnition/_util/cache/__init__.py
cellnition/_util/cache/utilcachecall.py
cellnition/_util/path/__init__.py
cellnition/_util/path/utilpathmake.py
cellnition/_util/path/utilpathself.py
cellnition/data/csv/.keep
cellnition/data/csv/MAPK_Cancer_Mo.csv
cellnition/data/png/cellnition_icon.png
cellnition/data/png/glyph_stability/glyph_attractor.png
cellnition/data/png/glyph_stability/glyph_attractor_limit_cycle.png
cellnition/data/png/glyph_stability/glyph_hidden.png
cellnition/data/png/glyph_stability/glyph_limit_cycle.png
cellnition/data/png/glyph_stability/glyph_repellor.png
cellnition/data/png/glyph_stability/glyph_repellor_limit_cycle.png
cellnition/data/png/glyph_stability/glyph_saddle.png
cellnition/data/png/glyph_stability/glyph_unknown.png
cellnition/science/__init__.py
cellnition/science/network_workflow.py
cellnition/science/network_models/__init__.py
cellnition/science/network_models/basic_network.py
cellnition/science/network_models/boolean_networks.py
cellnition/science/network_models/interaction_functions.py
cellnition/science/network_models/network_abc.py
cellnition/science/network_models/network_enums.py
cellnition/science/network_models/network_library.py
cellnition/science/network_models/probability_networks.py
cellnition/science/networks_toolbox/__init__.py
cellnition/science/networks_toolbox/boolean_state_machine.py
cellnition/science/networks_toolbox/gene_knockout.py
cellnition/science/networks_toolbox/netplot.py
cellnition/science/networks_toolbox/phase_space_searches.py
cellnition/science/networks_toolbox/phase_space_viz.py
cellnition/science/networks_toolbox/state_machine.py
cellnition/science/osmoadaptation/__init__.py
cellnition/science/osmoadaptation/analytic_model.py
cellnition/science/osmoadaptation/model_params.py
cellnition/science/osmoadaptation/osmo_model.py
cellnition-0.6.0.dist-info/METADATA
cellnition-0.6.0.dist-info/WHEEL
cellnition-0.6.0.dist-info/licenses/LICENSE
cellnition-0.6.0.dist-info/RECORD
