Metadata-Version: 2.4
Name: cellnition
Version: 0.6.0
Summary: Open-source cross-platform biology simulator analyzing gene regulatory networks (GRNs) with Network Finite State Machines (NFSMs).
Project-URL: Docs, https://betsee.github.io/cellnition
Project-URL: GitHub, https://github.com/betsee/cellnition
Project-URL: Forums, https://github.com/betsee/cellnition/discussions
Project-URL: Issues, https://github.com/betsee/cellnition/issues
Project-URL: Releases, https://github.com/betsee/cellnition/releases
Author-email: Alexis Pietak <alexis.pietak@gmail.com>
Maintainer-email: Cecil Curry <leycec@gmail.com>
License: Tufts Open Source License Rider v.1
License-File: LICENSE
Keywords: biology,python,science,simulator
Classifier: Development Status :: 5 - Production/Stable
Classifier: Intended Audience :: Science/Research
Classifier: License :: OSI Approved :: Apache Software License
Classifier: Natural Language :: English
Classifier: Operating System :: OS Independent
Classifier: Programming Language :: Python :: 3 :: Only
Classifier: Topic :: Scientific/Engineering :: Bio-Informatics
Requires-Python: >=3.10
Requires-Dist: beartype>=0.15.0
Requires-Dist: networkx>=3.4.0
Requires-Dist: numpy>=1.22.0
Requires-Dist: pandas>=1.5.0
Requires-Dist: pygraphviz>=1.10
Requires-Dist: pyvista>=0.42.0
Requires-Dist: scipy>=1.7.0
Requires-Dist: sympy>=1.9.0
Provides-Extra: dev
Requires-Dist: coverage>=5.5; extra == 'dev'
Requires-Dist: mkdocs-material>=9.6.0; extra == 'dev'
Requires-Dist: mkdocstrings-python>=1.16.0; extra == 'dev'
Requires-Dist: pytest>=4.0.0; extra == 'dev'
Requires-Dist: tox>=3.20.1; extra == 'dev'
Provides-Extra: docs
Requires-Dist: mkdocs-material>=9.6.0; extra == 'docs'
Requires-Dist: mkdocstrings-python>=1.16.0; extra == 'docs'
Provides-Extra: test
Requires-Dist: coverage>=5.5; extra == 'test'
Requires-Dist: pytest>=4.0.0; extra == 'test'
Requires-Dist: tox>=3.20.1; extra == 'test'
Provides-Extra: test-tox
Requires-Dist: pytest>=4.0.0; extra == 'test-tox'
Provides-Extra: test-tox-coverage
Requires-Dist: coverage>=5.5; extra == 'test-tox-coverage'
